py_ssh_echo/__init__.py
py_ssh_echo/server.py
py_ssh_echo-0.0.1.dist-info/METADATA
py_ssh_echo-0.0.1.dist-info/WHEEL
py_ssh_echo-0.0.1.dist-info/licenses/LICENSE
py_ssh_echo-0.0.1.dist-info/RECORD
