Metadata-Version: 2.4
Name: py-ssh-echo
Version: 0.0.1
Summary: A ssh echo server which provides an interactive shell
Project-URL: Homepage, https://github.com/namedchris/py-ssh-echo/
Project-URL: Issues, https://github.com/namedchris/py-ssh-echo//issues
Author-email: Chris Morgan <crmorgan1@gmail.com>
License-Expression: MIT
License-File: LICENSE
Classifier: Operating System :: OS Independent
Classifier: Programming Language :: Python :: 3
Requires-Python: >=3.9
